image2layout_computer_vision/sandbox.py
image2layout_computer_vision/sandbox_async.py
image2layout_computer_vision/sandbox_color.py
image2layout_computer_vision/sandbox_ocr.py
image2layout_computer_vision/sandbox_ocr_async.py
image2layout_computer_vision/sandbox_yolov6.py
image2layout_computer_vision/test_color.py
image2layout_computer_vision/test_ocr.py
image2layout_computer_vision/image2layout_computer_vision/README.md
image2layout_computer_vision/image2layout_computer_vision/__init__.py
image2layout_computer_vision/image2layout_computer_vision/requirements.txt
image2layout_computer_vision/image2layout_computer_vision/yolov6/class_names.txt
image2layout_computer_vision/image2layout_computer_vision/yolov6/data_image2layoutH.yaml
image2layout_computer_vision/image2layout_computer_vision/yolov6/data_image2layoutJ.yaml
image2layout_computer_vision-0.1.10.data/data/txt/class_names.txt
image2layout_computer_vision-0.1.10.data/data/yaml/data_image2layoutH.yaml
image2layout_computer_vision-0.1.10.data/data/yaml/data_image2layoutJ.yaml
image2layout_computer_vision-0.1.10.dist-info/LICENSE
image2layout_computer_vision-0.1.10.dist-info/METADATA
image2layout_computer_vision-0.1.10.dist-info/WHEEL
image2layout_computer_vision-0.1.10.dist-info/top_level.txt
image2layout_computer_vision-0.1.10.dist-info/RECORD
