Metadata-Version: 2.1
Name: image2layout_computer_vision
Version: 0.1.10
Summary: image processing and stuff
Home-page: https://github.com/felix-do-wizardry/image2layout-computer-vision
Author: Felix Do
Author-email: Felix Do <felix.do.1030@gmail.com>
Project-URL: Homepage, https://github.com/felix-do-wizardry/image2layout-computer-vision
Project-URL: Bug Tracker, https://github.com/felix-do-wizardry/image2layout-computer-vision
Classifier: Programming Language :: Python :: 3
Classifier: License :: OSI Approved :: MIT License
Classifier: Operating System :: OS Independent
Requires-Python: >=3.8
License-File: LICENSE
